invoice_creator/main.py
invoice_creator/quickstart.py
google_calendar_invoices-0.1.1.dist-info/LICENSE
google_calendar_invoices-0.1.1.dist-info/METADATA
google_calendar_invoices-0.1.1.dist-info/WHEEL
google_calendar_invoices-0.1.1.dist-info/entry_points.txt
google_calendar_invoices-0.1.1.dist-info/top_level.txt
google_calendar_invoices-0.1.1.dist-info/RECORD
