Metadata-Version: 2.1
Name: google-calendar-invoices
Version: 0.1.1
Summary: A tool to generate invoices from Google Calendar events
Author-email: Sahil Goonraz <sahilgoonrazk@gmail.com>
License: MIT License
Project-URL: Homepage, https://github.com/skg17/invoice-creator
Project-URL: Repository, https://github.com/skg17/invoice-creator
Project-URL: Documentation, https://github.com/skg17/invoice-creator#readme
Requires-Python: >=3.7
License-File: LICENSE
Requires-Dist: google-auth >=2.0.0
Requires-Dist: google-auth-oauthlib >=0.4.4
Requires-Dist: google-api-python-client >=2.0.2
Requires-Dist: jinja2 >=3.0.0
Requires-Dist: pdfkit >=1.0.0
